pylhc_submitter/__init__.py
pylhc_submitter/autosix.py
pylhc_submitter/job_submitter.py
pylhc_submitter/constants/__init__.py
pylhc_submitter/constants/autosix.py
pylhc_submitter/constants/external_paths.py
pylhc_submitter/constants/general.py
pylhc_submitter/constants/htcondor.py
pylhc_submitter/constants/job_submitter.py
pylhc_submitter/sixdesk_tools/__init__.py
pylhc_submitter/sixdesk_tools/create_workspace.py
pylhc_submitter/sixdesk_tools/extract_data_from_db.py
pylhc_submitter/sixdesk_tools/mask_sixdeskenv
pylhc_submitter/sixdesk_tools/mask_sysenv
pylhc_submitter/sixdesk_tools/post_process_da.py
pylhc_submitter/sixdesk_tools/stages.py
pylhc_submitter/sixdesk_tools/submit.py
pylhc_submitter/sixdesk_tools/troubleshooting.py
pylhc_submitter/sixdesk_tools/utils.py
pylhc_submitter/submitter/__init__.py
pylhc_submitter/submitter/htc_utils.py
pylhc_submitter/submitter/iotools.py
pylhc_submitter/submitter/mask.py
pylhc_submitter/submitter/runners.py
pylhc_submitter/utils/__init__.py
pylhc_submitter/utils/environment.py
pylhc_submitter/utils/iotools.py
pylhc_submitter/utils/logging_tools.py
pylhc_submitter-2.0.6.dist-info/METADATA
pylhc_submitter-2.0.6.dist-info/WHEEL
pylhc_submitter-2.0.6.dist-info/licenses/LICENSE
pylhc_submitter-2.0.6.dist-info/RECORD
