Metadata-Version: 2.4
Name: pylhc_submitter
Version: 2.0.6
Summary: pylhc-submitter contains scripts to simplify the creation and submission of jobs to HTCondor at CERN
Project-URL: homepage, https://github.com/pylhc/submitter
Project-URL: repository, https://github.com/pylhc/submitter
Project-URL: documentation, https://pylhc.github.io/submitter/
Project-URL: changelog, https://github.com/pylhc/submitter/blob/master/CHANGELOG.md
Author-email: OMC Team <pylhc@github.com>
License-Expression: MIT
License-File: LICENSE
Classifier: Intended Audience :: Science/Research
Classifier: License :: OSI Approved :: MIT License
Classifier: Natural Language :: English
Classifier: Operating System :: OS Independent
Classifier: Programming Language :: Python :: 3 :: Only
Classifier: Programming Language :: Python :: 3.10
Classifier: Programming Language :: Python :: 3.11
Classifier: Programming Language :: Python :: 3.12
Classifier: Programming Language :: Python :: 3.13
Classifier: Programming Language :: Python :: 3.14
Classifier: Programming Language :: Python :: Implementation :: CPython
Classifier: Topic :: Software Development :: Libraries :: Python Modules
Classifier: Typing :: Typed
Requires-Python: >=3.10
Requires-Dist: generic-parser>=1.1
Requires-Dist: htcondor>=8.9.2; sys_platform == 'linux'
Requires-Dist: matplotlib>=3.8
Requires-Dist: numpy>=1.24
Requires-Dist: pandas>=2.1
Requires-Dist: scipy>=1.10
Requires-Dist: tfs-pandas>=3.8
Provides-Extra: all
Requires-Dist: pytest-cov>=2.9; extra == 'all'
Requires-Dist: pytest-mpl>=0.15; extra == 'all'
Requires-Dist: pytest>=7.0; extra == 'all'
Requires-Dist: sphinx-rtd-theme>=2.0; extra == 'all'
Requires-Dist: sphinx>=7.0; extra == 'all'
Provides-Extra: doc
Requires-Dist: sphinx-rtd-theme>=2.0; extra == 'doc'
Requires-Dist: sphinx>=7.0; extra == 'doc'
Provides-Extra: test
Requires-Dist: pytest-cov>=2.9; extra == 'test'
Requires-Dist: pytest-mpl>=0.15; extra == 'test'
Requires-Dist: pytest>=7.0; extra == 'test'
